mini_racer-0.14.0.data/purelib/py_mini_racer/__about__.py
mini_racer-0.14.0.data/purelib/py_mini_racer/__init__.py
mini_racer-0.14.0.data/purelib/py_mini_racer/_context.py
mini_racer-0.14.0.data/purelib/py_mini_racer/_dll.py
mini_racer-0.14.0.data/purelib/py_mini_racer/_exc.py
mini_racer-0.14.0.data/purelib/py_mini_racer/_mini_racer.py
mini_racer-0.14.0.data/purelib/py_mini_racer/_objects.py
mini_racer-0.14.0.data/purelib/py_mini_racer/_set_timeout.py
mini_racer-0.14.0.data/purelib/py_mini_racer/_types.py
mini_racer-0.14.0.data/purelib/py_mini_racer/_value_handle.py
mini_racer-0.14.0.data/purelib/py_mini_racer/icudtl.dat
mini_racer-0.14.0.data/purelib/py_mini_racer/libmini_racer.dylib
mini_racer-0.14.0.data/purelib/py_mini_racer/py.typed
mini_racer-0.14.0.dist-info/licenses/AUTHORS.md
mini_racer-0.14.0.dist-info/licenses/LICENSE
mini_racer-0.14.0.dist-info/METADATA
mini_racer-0.14.0.dist-info/WHEEL
mini_racer-0.14.0.dist-info/top_level.txt
mini_racer-0.14.0.dist-info/RECORD
