Metadata-Version: 2.4
Name: mini-racer
Version: 0.14.0
Summary: Minimal, modern embedded V8 for Python.
Author-email: bpcreech <mini-racer@bpcreech.com>, Sqreen <support@sqreen.com>
License-Expression: ISC
Project-URL: Homepage, https://github.com/bpcreech/PyMiniRacer
Keywords: py_mini_racer
Classifier: Development Status :: 5 - Production/Stable
Classifier: Intended Audience :: Developers
Classifier: Natural Language :: English
Classifier: Programming Language :: Python :: 3
Requires-Python: >=3.10
License-File: LICENSE
License-File: AUTHORS.md
Dynamic: description
Dynamic: description-content-type
Dynamic: license-file
